{"11000":{"numericValue":1163480295803,"fiscalDate":"2018-12-31"},"11100":{"numericValue":25396934265,"fiscalDate":"2018-12-31"},"11110":{"numericValue":23245934265,"fiscalDate":"2018-12-31"},"11120":{"numericValue":2151000000,"fiscalDate":"2018-12-31"},"11200":{"numericValue":50410000000,"fiscalDate":"2018-12-31"},"11210":{"numericValue":600000000,"fiscalDate":"2018-12-31"},"11290":{"numericValue":0,"fiscalDate":"2018-12-31"},"11300":{"numericValue":882777671254,"fiscalDate":"2018-12-31"},"11310":{"numericValue":488479895810,"fiscalDate":"2018-12-31"},"11320":{"numericValue":280090702740,"fiscalDate":"2018-12-31"},"11330":{"numericValue":0,"fiscalDate":"2018-12-31"},"11340":{"numericValue":0,"fiscalDate":"2018-12-31"},"11345":{"numericValue":17995145635,"fiscalDate":"2018-12-31"},"11350":{"numericValue":101131968473,"fiscalDate":"2018-12-31"},"11390":{"numericValue":-4920041404,"fiscalDate":"2018-12-31"},"11400":{"numericValue":187689478091,"fiscalDate":"2018-12-31"},"11410":{"numericValue":187689478091,"fiscalDate":"2018-12-31"},"11490":{"numericValue":0,"fiscalDate":"2018-12-31"},"11500":{"numericValue":17206212193,"fiscalDate":"2018-12-31"},"11510":{"numericValue":4308551932,"fiscalDate":"2018-12-31"},"11520":{"numericValue":11359078930,"fiscalDate":"2018-12-31"},"11540":{"numericValue":1174197208,"fiscalDate":"2018-12-31"},"11570":{"numericValue":0,"fiscalDate":"2018-12-31"},"11580":{"numericValue":364384123,"fiscalDate":"2018-12-31"},"12000":{"numericValue":295677153703,"fiscalDate":"2018-12-31"},"12100":{"numericValue":0,"fiscalDate":"2018-12-31"},"12110":{"numericValue":0,"fiscalDate":"2018-12-31"},"12111":{"numericValue":0,"fiscalDate":"2018-12-31"},"12120":{"numericValue":0,"fiscalDate":"2018-12-31"},"12130":{"numericValue":0,"fiscalDate":"2018-12-31"},"12140":{"numericValue":0,"fiscalDate":"2018-12-31"},"12180":{"numericValue":0,"fiscalDate":"2018-12-31"},"12190":{"numericValue":0,"fiscalDate":"2018-12-31"},"12200":{"numericValue":198259508067,"fiscalDate":"2018-12-31"},"12210":{"numericValue":179541072489,"fiscalDate":"2018-12-31"},"12220":{"numericValue":277278166839,"fiscalDate":"2018-12-31"},"12230":{"numericValue":-97737094350,"fiscalDate":"2018-12-31"},"12240":{"numericValue":18718435578,"fiscalDate":"2018-12-31"},"12250":{"numericValue":23957487275,"fiscalDate":"2018-12-31"},"12260":{"numericValue":-5239051697,"fiscalDate":"2018-12-31"},"12270":{"numericValue":0,"fiscalDate":"2018-12-31"},"12280":{"numericValue":0,"fiscalDate":"2018-12-31"},"12290":{"numericValue":0,"fiscalDate":"2018-12-31"},"12300":{"numericValue":0,"fiscalDate":"2018-12-31"},"12400":{"numericValue":0,"fiscalDate":"2018-12-31"},"12410":{"numericValue":0,"fiscalDate":"2018-12-31"},"12420":{"numericValue":0,"fiscalDate":"2018-12-31"},"12440":{"numericValue":5589448129,"fiscalDate":"2018-12-31"},"12450":{"numericValue":0,"fiscalDate":"2018-12-31"},"12460":{"numericValue":5589448129,"fiscalDate":"2018-12-31"},"12500":{"numericValue":67284008510,"fiscalDate":"2018-12-31"},"12510":{"numericValue":660866342,"fiscalDate":"2018-12-31"},"12520":{"numericValue":34833118056,"fiscalDate":"2018-12-31"},"12580":{"numericValue":31862375684,"fiscalDate":"2018-12-31"},"12590":{"numericValue":-72351572,"fiscalDate":"2018-12-31"},"12595":{"numericValue":0,"fiscalDate":"2018-12-31"},"12600":{"numericValue":24544188997,"fiscalDate":"2018-12-31"},"12610":{"numericValue":24160463613,"fiscalDate":"2018-12-31"},"12620":{"numericValue":299425384,"fiscalDate":"2018-12-31"},"12630":{"numericValue":0,"fiscalDate":"2018-12-31"},"12680":{"numericValue":84300000,"fiscalDate":"2018-12-31"},"12690":{"numericValue":0,"fiscalDate":"2018-12-31"},"12700":{"numericValue":1459157449506,"fiscalDate":"2018-12-31"},"13000":{"numericValue":1172161523654,"fiscalDate":"2018-12-31"},"13100":{"numericValue":1113925393125,"fiscalDate":"2018-12-31"},"13110":{"numericValue":898875944704,"fiscalDate":"2018-12-31"},"13120":{"numericValue":109623019046,"fiscalDate":"2018-12-31"},"13130":{"numericValue":46895599274,"fiscalDate":"2018-12-31"},"13140":{"numericValue":2051805182,"fiscalDate":"2018-12-31"},"13150":{"numericValue":2303176570,"fiscalDate":"2018-12-31"},"13160":{"numericValue":12917360063,"fiscalDate":"2018-12-31"},"13170":{"numericValue":0,"fiscalDate":"2018-12-31"},"13180":{"numericValue":0,"fiscalDate":"2018-12-31"},"13190":{"numericValue":41232622084,"fiscalDate":"2018-12-31"},"13197":{"numericValue":0,"fiscalDate":"2018-12-31"},"13199":{"numericValue":0,"fiscalDate":"2018-12-31"},"13200":{"numericValue":0,"fiscalDate":"2018-12-31"},"13210":{"numericValue":0,"fiscalDate":"2018-12-31"},"13220":{"numericValue":0,"fiscalDate":"2018-12-31"},"13300":{"numericValue":58236130529,"fiscalDate":"2018-12-31"},"13310":{"numericValue":0,"fiscalDate":"2018-12-31"},"13311":{"numericValue":0,"fiscalDate":"2018-12-31"},"13312":{"numericValue":0,"fiscalDate":"2018-12-31"},"13313":{"numericValue":0,"fiscalDate":"2018-12-31"},"13320":{"numericValue":0,"fiscalDate":"2018-12-31"},"13330":{"numericValue":0,"fiscalDate":"2018-12-31"},"13340":{"numericValue":58214236547,"fiscalDate":"2018-12-31"},"13343":{"numericValue":0,"fiscalDate":"2018-12-31"},"13346":{"numericValue":0,"fiscalDate":"2018-12-31"},"13350":{"numericValue":21893982,"fiscalDate":"2018-12-31"},"13360":{"numericValue":0,"fiscalDate":"2018-12-31"},"13370":{"numericValue":0,"fiscalDate":"2018-12-31"},"14000":{"numericValue":286995925852,"fiscalDate":"2018-12-31"},"14100":{"numericValue":286995925852,"fiscalDate":"2018-12-31"},"14110":{"numericValue":265858400000,"fiscalDate":"2018-12-31"},"14120":{"numericValue":1397230362,"fiscalDate":"2018-12-31"},"14130":{"numericValue":0,"fiscalDate":"2018-12-31"},"14140":{"numericValue":-5724227833,"fiscalDate":"2018-12-31"},"14145":{"numericValue":5012800000,"fiscalDate":"2018-12-31"},"14148":{"numericValue":260845600000,"fiscalDate":"2018-12-31"},"14149":{"numericValue":0,"fiscalDate":"2018-12-31"},"14150":{"numericValue":0,"fiscalDate":"2018-12-31"},"14160":{"numericValue":0,"fiscalDate":"2018-12-31"},"14170":{"numericValue":4527251411,"fiscalDate":"2018-12-31"},"14180":{"numericValue":0,"fiscalDate":"2018-12-31"},"14190":{"numericValue":0,"fiscalDate":"2018-12-31"},"14191":{"numericValue":4527251411,"fiscalDate":"2018-12-31"},"14193":{"numericValue":0,"fiscalDate":"2018-12-31"},"14200":{"numericValue":9904410665,"fiscalDate":"2018-12-31"},"14201":{"numericValue":0,"fiscalDate":"2018-12-31"},"14210":{"numericValue":0,"fiscalDate":"2018-12-31"},"14220":{"numericValue":5616380797,"fiscalDate":"2018-12-31"},"14230":{"numericValue":4288029868,"fiscalDate":"2018-12-31"},"14240":{"numericValue":11032861247,"fiscalDate":"2018-12-31"},"14300":{"numericValue":0,"fiscalDate":"2018-12-31"},"14310":{"numericValue":25866202,"fiscalDate":"2018-12-31"},"14320":{"numericValue":0,"fiscalDate":"2018-12-31"},"14330":{"numericValue":0,"fiscalDate":"2018-12-31"},"14400":{"numericValue":1459157449506,"fiscalDate":"2018-12-31"},"15000":{"numericValue":0,"fiscalDate":"2018-12-31"},"21000":{"numericValue":534100116055,"fiscalDate":"2018-12-31"},"21001":{"numericValue":533545219573,"fiscalDate":"2018-12-31"},"21090":{"numericValue":554896482,"fiscalDate":"2018-12-31"},"21500":{"numericValue":1730648338,"fiscalDate":"2018-12-31"},"21900":{"numericValue":445139219,"fiscalDate":"2018-12-31"},"22051":{"numericValue":489381946,"fiscalDate":"2018-12-31"},"22052":{"numericValue":0,"fiscalDate":"2018-12-31"},"22070":{"numericValue":489381946,"fiscalDate":"2018-12-31"},"22100":{"numericValue":498378942502,"fiscalDate":"2018-12-31"},"22110":{"numericValue":2394517624,"fiscalDate":"2018-12-31"},"22200":{"numericValue":10362257696,"fiscalDate":"2018-12-31"},"22230":{"numericValue":0,"fiscalDate":"2018-12-31"},"22500":{"numericValue":22451341466,"fiscalDate":"2018-12-31"},"22509":{"numericValue":0,"fiscalDate":"2018-12-31"},"22510":{"numericValue":19251753968,"fiscalDate":"2018-12-31"},"22515":{"numericValue":0,"fiscalDate":"2018-12-31"},"22900":{"numericValue":45491226,"fiscalDate":"2018-12-31"},"23000":{"numericValue":2443826358,"fiscalDate":"2018-12-31"},"23001":{"numericValue":0,"fiscalDate":"2018-12-31"},"23003":{"numericValue":1599074670,"fiscalDate":"2018-12-31"},"23100":{"numericValue":35166277071,"fiscalDate":"2018-12-31"},"23110":{"numericValue":1688808623,"fiscalDate":"2018-12-31"},"23200":{"numericValue":0,"fiscalDate":"2018-12-31"},"23300":{"numericValue":0,"fiscalDate":"2018-12-31"},"23500":{"numericValue":-844751688,"fiscalDate":"2018-12-31"},"23800":{"numericValue":2088456616,"fiscalDate":"2018-12-31"},"23810":{"numericValue":0,"fiscalDate":"2018-12-31"},"23900":{"numericValue":399647993,"fiscalDate":"2018-12-31"},"30100":{"numericValue":858036622859,"fiscalDate":"2018-12-31"},"30200":{"numericValue":-702577321702,"fiscalDate":"2018-12-31"},"30300":{"numericValue":-3749431578,"fiscalDate":"2018-12-31"},"30400":{"numericValue":-17842997076,"fiscalDate":"2018-12-31"},"30500":{"numericValue":-108377435,"fiscalDate":"2018-12-31"},"30600":{"numericValue":86686128583,"fiscalDate":"2018-12-31"},"30700":{"numericValue":-232116714766,"fiscalDate":"2018-12-31"},"31100":{"numericValue":0,"fiscalDate":"2018-12-31"},"31101":{"numericValue":0,"fiscalDate":"2018-12-31"},"31102":{"numericValue":0,"fiscalDate":"2018-12-31"},"31110":{"numericValue":0,"fiscalDate":"2018-12-31"},"31111":{"numericValue":0,"fiscalDate":"2018-12-31"},"31120":{"numericValue":0,"fiscalDate":"2018-12-31"},"31130":{"numericValue":0,"fiscalDate":"2018-12-31"},"31140":{"numericValue":0,"fiscalDate":"2018-12-31"},"31150":{"numericValue":0,"fiscalDate":"2018-12-31"},"31160":{"numericValue":0,"fiscalDate":"2018-12-31"},"31170":{"numericValue":0,"fiscalDate":"2018-12-31"},"31180":{"numericValue":0,"fiscalDate":"2018-12-31"},"31190":{"numericValue":0,"fiscalDate":"2018-12-31"},"31200":{"numericValue":0,"fiscalDate":"2018-12-31"},"32000":{"numericValue":-11672091115,"fiscalDate":"2018-12-31"},"32100":{"numericValue":0,"fiscalDate":"2018-12-31"},"32200":{"numericValue":0,"fiscalDate":"2018-12-31"},"32300":{"numericValue":-2100000000,"fiscalDate":"2018-12-31"},"32400":{"numericValue":0,"fiscalDate":"2018-12-31"},"32500":{"numericValue":0,"fiscalDate":"2018-12-31"},"32600":{"numericValue":0,"fiscalDate":"2018-12-31"},"32700":{"numericValue":327192,"fiscalDate":"2018-12-31"},"33000":{"numericValue":-2099672808,"fiscalDate":"2018-12-31"},"33100":{"numericValue":0,"fiscalDate":"2018-12-31"},"33200":{"numericValue":0,"fiscalDate":"2018-12-31"},"33300":{"numericValue":583365244347,"fiscalDate":"2018-12-31"},"33400":{"numericValue":-552299299478,"fiscalDate":"2018-12-31"},"33500":{"numericValue":-68140983,"fiscalDate":"2018-12-31"},"33600":{"numericValue":0,"fiscalDate":"2018-12-31"},"33710":{"numericValue":0,"fiscalDate":"2018-12-31"},"34000":{"numericValue":30997803886,"fiscalDate":"2018-12-31"},"35000":{"numericValue":17226039963,"fiscalDate":"2018-12-31"},"36000":{"numericValue":8170894302,"fiscalDate":"2018-12-31"},"36100":{"numericValue":0,"fiscalDate":"2018-12-31"},"37000":{"numericValue":25396934265,"fiscalDate":"2018-12-31"},"412320":{"numericValue":49810000000,"fiscalDate":"2018-12-31"},"412541":{"numericValue":0,"fiscalDate":"2018-12-31"},"431100":{"numericValue":0,"fiscalDate":"2018-12-31"},"431400":{"numericValue":0,"fiscalDate":"2018-12-31"},"611530":{"numericValue":0,"fiscalDate":"2018-12-31"},"700036":{"numericValue":0,"fiscalDate":"2018-12-31"},"700087":{"numericValue":0,"fiscalDate":"2018-12-31"}}