{"fiscalDates":["2013-03-31","2013-06-30","2013-09-30","2013-12-31","2014-03-31","2014-06-30"],"newFiscalDate":["2014-03-31","2014-06-30"],"newFiscalDateQuarter":["2014-03-31","2014-06-30"],"tiLeNovayRongVcsh":[671,676],"tiLePhaiThuTaiSan":[41,42],"tsTienTuongDuongTienDTTCNH":[6,3],"tsKhoanPhaiThu":[198,217],"tsHangTonKho":[216,239],"tsTaiSanCoDinh":[26,26],"tsTaiSanDoDangDaiHan":[0,0],"tsKhac":[31,38],"nvVonChuSoHuu":[30,30],"nvVayNganHan":[159,158],"nvVayDaiHanTPCD":[50,50],"nvMuaTraTienTruocDtChuaTH":[64,100],"nvKhac":[174,185],"nvTileVayRongVCSHQ":[671,676],"tangTruongDoanhSoThuanYoY":[-58,85],"tangTruongDoanhThuanKep":[-5,-5],"tangTruongDoanhThuanKepNum":-5,"doanhSoThuan":[22,40],"tangTruongLNSTYoY":[-101,-101],"tangTruongLNSTCtyMeNam":[null,null],"tangTruongLNSTCtyMe5Year":null,"lnst":[0,0],"bienLoiNhuanGop":[25,21],"bienLoiNhuanRong":[0,0],"ROACuoiKy":[-5.8,-2.5],"ROECuoiKy":[-92,-43],"choNhanGiaRaPE":-0.8434549600109017,"choNhanGiaRaPB":0.3632458806309608,"choNhanGiaRaPS":0.09783362065797217,"PE":[null,null],"PETb":[null,null],"PB":[null,null],"PBTb":[null,null],"PS":[null,null],"PSTb":[null,null],"soCoPhieuLuuHanh":11000000,"isNganHang":false,"isChungKhoan":false,"tangTruongHangTonKhoKep":5,"lctThuanHDSXKD":[2,-2],"lctThuanHDDauTu":[0,0],"lctThuanHDTC":[2,-2],"lctThuanTrongKy":[3,-4],"hangTonKho":[216,239],"hangTonKhoVongQuay":[0.5,0.5],"coTucLNST":[12,-29,-36,-37,-19,-21,1,1],"coTucDaTra":[4,1,0,0,0,0,0,0],"coTucTiLeDaTra":[33,-4,0,0,0,0,0,0],"newFiscalDateYear":["2010-12-31","2011-12-31","2012-12-31","2013-12-31","2014-12-31","2015-12-31","2016-12-31","2017-12-31"]}