{
  "fiscalDates": [
    "2007-12-31",
    "2008-12-31",
    "2009-12-31",
    "2010-12-31",
    "2011-12-31",
    "2012-12-31",
    "2013-12-31",
    "2014-12-31",
    "2015-12-31",
    "2016-12-31",
    "2017-12-31",
    "2018-12-31",
    "2019-12-31",
    "2020-12-31",
    "2021-12-31",
    "2022-12-31",
    "2023-12-31",
    "2024-12-31",
    "2025-12-31"
  ],
  "newFiscalDate": [
    "2008-12-31",
    "2009-12-31",
    "2010-12-31",
    "2011-12-31",
    "2012-12-31",
    "2013-12-31",
    "2014-12-31",
    "2015-12-31",
    "2016-12-31",
    "2017-12-31",
    "2018-12-31",
    "2019-12-31",
    "2020-12-31",
    "2021-12-31",
    "2022-12-31",
    "2023-12-31",
    "2024-12-31",
    "2025-12-31"
  ],
  "tiLeNovayRongVcsh": [
    0,
    0,
    0,
    0,
    0,
    0,
    0,
    0,
    0,
    0,
    0,
    0,
    0,
    0,
    0,
    0,
    0,
    0
  ],
  "tiLePhaiThuTaiSan": [
    0,
    0,
    0,
    0,
    0,
    0,
    0,
    0,
    0,
    0,
    0,
    0,
    0,
    0,
    0,
    0,
    0,
    0
  ],
  "nhTsChoVayKhachHang": [
    7507,
    9465,
    20189,
    19313,
    16230,
    20423,
    31568,
    42439,
    58445,
    69921,
    83008,
    97484,
    107761,
    125807,
    151523,
    176774,
    206073,
    233780
  ],
  "nhTsTienGuiChoVayTCTDkhac": [
    9160,
    14383,
    13464,
    42118,
    37343,
    31346,
    26148,
    11892,
    15215,
    17230,
    19140,
    25400,
    25741,
    42590,
    45068,
    48699,
    70244,
    91447
  ],
  "nhTsChungKhoanDauTu": [
    2340,
    2292,
    15149,
    13983,
    12125,
    18234,
    12251,
    17526,
    19732,
    22060,
    20534,
    20654,
    32180,
    16820,
    8647,
    14287,
    19632,
    25442
  ],
  "nhTsChungKhoanKinhDoanh": [
    725,
    491,
    1418,
    60,
    10,
    20,
    9,
    0,
    0,
    4460,
    7222,
    1263,
    2694,
    13083,
    3987,
    8353,
    8867,
    11445
  ],
  "nhTsTienVangTienGuiNHNN": [
    257,
    1694,
    1431,
    19586,
    1764,
    1785,
    3906,
    6649,
    3073,
    4145,
    2725,
    4522,
    4387,
    5875,
    10865,
    3651,
    12263,
    25513
  ],
  "nhTsKhac": [
    2279,
    2273,
    3591,
    6032,
    7594,
    8056,
    6302,
    6251,
    6899,
    7193,
    7858,
    8075,
    7444,
    7489,
    11333,
    14358,
    8619,
    8815
  ],
  "nhTsTiLeLaiPhiTongTaiSan": [
    1.55,
    0.98,
    1.64,
    1.64,
    3.67,
    2.25,
    2.12,
    2.25,
    2.06,
    2.02,
    2.02,
    2.15,
    1.44,
    0.79,
    1.12,
    1.25,
    0.79,
    0.78
  ],
  "nhNvPhatHanhGtoCoGia": [
    1000,
    0,
    17,
    8300,
    2800,
    2000,
    2900,
    2900,
    2900,
    3728,
    8105,
    15679,
    7065,
    19053,
    21505,
    16846,
    30450,
    29984
  ],
  "nhNvTienGuiKhachHang": [
    8587,
    12346,
    24790,
    34353,
    31447,
    36183,
    45030,
    57018,
    72131,
    80040,
    84345,
    95727,
    113277,
    109785,
    115547,
    144840,
    168320,
    191807
  ],
  "nhNvGuiVayTCTDKhac": [
    8143,
    12297,
    14895,
    47264,
    31370,
    33761,
    25596,
    18073,
    20779,
    32602,
    29249,
    31470,
    42517,
    58366,
    59720,
    66698,
    85304,
    107281
  ],
  "nhNvKhoanNoCpNhnnVN": [
    0,
    0,
    8879,
    4601,
    1844,
    496,
    0,
    181,
    348,
    311,
    7282,
    239,
    206,
    2173,
    3839,
    2539,
    2064,
    20819
  ],
  "nhNvVcsh": [
    4029,
    5481,
    5743,
    5537,
    5582,
    5726,
    5682,
    5769,
    5880,
    6175,
    8302,
    10926,
    13670,
    18663,
    26232,
    30297,
    35003,
    40373
  ],
  "nhNvKhac": [
    509,
    472,
    917,
    1038,
    2025,
    1698,
    975,
    815,
    1327,
    2155,
    3205,
    3358,
    3473,
    3624,
    4581,
    4902,
    4557,
    6179
  ],
  "nhTsTiLeTaiSanVcsh": [
    5.5,
    5.6,
    9.6,
    18.3,
    13.4,
    13.9,
    14.1,
    14.7,
    17.6,
    20.2,
    16.9,
    14.4,
    13.2,
    11.3,
    8.8,
    8.8,
    9.3,
    9.8
  ],
  "nhToiTangTruongYoy5Nam": 25,
  "nhToiThuNhapLaiThuan": [
    646,
    721,
    0,
    850,
    1158,
    862,
    724,
    1147,
    1843,
    1972,
    2337,
    2895,
    3062,
    5186,
    7006,
    7071,
    9966,
    9704
  ],
  "nhToiLaiThuanTuHDDV": [
    108,
    89,
    205,
    56,
    26,
    28,
    39,
    41,
    44,
    65,
    186,
    335,
    356,
    1146,
    1367,
    1308,
    1112,
    725
  ],
  "nhToiThuNhapTuHDKhac": [
    -282,
    -811,
    -205,
    -92,
    -16,
    185,
    329,
    -9,
    26,
    158,
    289,
    1981,
    1166,
    704,
    1274,
    1045,
    1331,
    3685
  ],
  "nhToiTangTruongYoy": [
    -15,
    -100,
    null,
    null,
    44,
    -8,
    2,
    8,
    62,
    15,
    28,
    85,
    -12,
    53,
    37,
    -2,
    32,
    14
  ],
  "tangTruongLNSTYoY": [
    -42,
    166,
    37,
    -80,
    -58,
    188,
    -43,
    6,
    27,
    161,
    62,
    123,
    24,
    92,
    55,
    -9,
    31,
    14
  ],
  "tangTruongLNSTCtyMeNam": [
    -29,
    -3,
    -28,
    -32,
    -2,
    42,
    27,
    66,
    71,
    86,
    68,
    49,
    34,
    32
  ],
  "tangTruongLNSTCtyMe5Year": 32,
  "lnst": [
    173,
    460,
    629,
    126,
    53,
    152,
    87,
    92,
    117,
    305,
    493,
    1098,
    1360,
    2607,
    4053,
    3677,
    4816,
    5510
  ],
  "nhTangTruongChoVayKhachHangKep5Nam": 17,
  "nhTangTruongChoVay5Year": [
    8.6,
    22.5,
    27.2,
    15.9,
    24.6,
    33.4,
    32,
    25.2,
    20.5,
    16.7,
    16.9,
    16.5,
    16.2,
    16.8
  ],
  "nhChoVayKhachHang": [
    7586,
    9626,
    20512,
    19641,
    16694,
    20929,
    32066,
    42806,
    58989,
    70526,
    83910,
    98614,
    108869,
    127588,
    153956,
    179752,
    209355,
    237047
  ],
  "nhTangTruongChoVayKhachHang": [
    -31,
    27,
    113,
    -4,
    -15,
    25,
    53,
    33,
    38,
    20,
    19,
    18,
    10,
    17,
    21,
    17,
    16,
    13
  ],
  "nhSlNIM": [
    3.3,
    2.7,
    0,
    1.1,
    1.8,
    1.2,
    1,
    1.6,
    1.9,
    1.7,
    1.8,
    2,
    1.8,
    2.6,
    3.3,
    2.8,
    3.2,
    2.7
  ],
  "nhSlYOAE": [
    15.1,
    6.1,
    7,
    9.8,
    12.8,
    6.8,
    5.9,
    6,
    6.5,
    6.4,
    6.6,
    7,
    6.3,
    5.9,
    7.2,
    7.9,
    6.7,
    6.7
  ],
  "nhSlCOF": [
    13.2,
    -3.7,
    -5,
    7,
    10.8,
    5.4,
    4.7,
    4.1,
    4.5,
    4.6,
    4.9,
    5.1,
    4.7,
    3.5,
    4.1,
    5.5,
    3.8,
    4.2
  ],
  "ROACuoiKy": [
    1.4,
    1.5,
    1.1,
    0.1,
    0.1,
    0.2,
    0.1,
    0.1,
    0.1,
    0.2,
    0.4,
    0.7,
    0.8,
    1.2,
    1.8,
    1.4,
    1.5,
    1.4
  ],
  "ROECuoiKy": [
    8,
    8.4,
    11,
    2.3,
    0.9,
    2.6,
    1.5,
    1.6,
    2,
    4.9,
    5.9,
    10.1,
    10,
    14,
    15.5,
    12.1,
    13.8,
    13.6
  ],
  "newFiscalDateQuarter": [
    "2016-03-31",
    "2016-06-30",
    "2016-09-30",
    "2016-12-31",
    "2017-03-31",
    "2017-06-30",
    "2017-09-30",
    "2017-12-31",
    "2018-03-31",
    "2018-06-30",
    "2018-09-30",
    "2018-12-31",
    "2019-03-31",
    "2019-06-30",
    "2019-09-30",
    "2019-12-31",
    "2020-03-31",
    "2020-06-30",
    "2020-09-30",
    "2020-12-31",
    "2021-03-31",
    "2021-06-30",
    "2021-09-30",
    "2021-12-31",
    "2022-03-31",
    "2022-06-30",
    "2022-09-30",
    "2022-12-31",
    "2023-03-31",
    "2023-06-30",
    "2023-09-30",
    "2023-12-31",
    "2024-03-31",
    "2024-06-30",
    "2024-09-30",
    "2024-12-31",
    "2025-03-31",
    "2025-06-30",
    "2025-09-30",
    "2025-12-31",
    "2026-03-31"
  ],
  "nhnxKyHanS": [
    "VAB",
    "SGB",
    "VBB",
    "STB",
    "ACB",
    "CTG",
    "BID",
    "BVB",
    "EIB",
    "PGB",
    "VCB",
    "LPB",
    "MBB",
    "NAB",
    "HDB",
    "KLB",
    "SSB",
    "BAB",
    "VIB",
    "VPB",
    "TCB",
    "TPB",
    "MSB",
    "SHB",
    "NVB",
    "OCB",
    "ABB"
  ],
  "nhnxKyHanNH": [
    {
      "y": 69.23779280019437,
      "color": "#908f8faa"
    },
    {
      "y": 68.81925911838876,
      "color": "#908f8faa"
    },
    {
      "y": 64.1061304666074,
      "color": "#908f8faa"
    },
    {
      "y": 63.613915060998885,
      "color": "#908f8faa"
    },
    {
      "y": 63.375223321126185,
      "color": "#908f8faa"
    },
    {
      "y": 61.41692178085697,
      "color": "#908f8faa"
    },
    {
      "y": 60.502137981678736,
      "color": "#908f8faa"
    },
    {
      "y": 59.49940833854521,
      "color": "#908f8faa"
    },
    {
      "y": 57.91191768365723,
      "color": "#908f8faa"
    },
    {
      "y": 57.7163602597739,
      "color": "#908f8faa"
    },
    {
      "y": 57.69450446222394,
      "color": "#908f8faa"
    },
    {
      "y": 54.039087460042346,
      "color": "#908f8faa"
    },
    {
      "y": 52.51030540259539,
      "color": "#908f8faa"
    },
    {
      "y": 50.9695938910387,
      "color": "#908f8faa"
    },
    {
      "y": 49.5163490310393,
      "color": "#908f8faa"
    },
    {
      "y": 48.10482333220131,
      "color": "#908f8faa"
    },
    {
      "y": 47.37912136013607,
      "color": "#ED7D31"
    },
    {
      "y": 42.999284630792715,
      "color": "#908f8faa"
    },
    {
      "y": 41.272666687114175,
      "color": "#908f8faa"
    },
    {
      "y": 39.79015916285892,
      "color": "#908f8faa"
    },
    {
      "y": 37.62172717050839,
      "color": "#908f8faa"
    },
    {
      "y": 36.76396250155236,
      "color": "#908f8faa"
    },
    {
      "y": 36.557651280451644,
      "color": "#908f8faa"
    },
    {
      "y": 34.79736312369433,
      "color": "#908f8faa"
    },
    {
      "y": 28.017031984694796,
      "color": "#908f8faa"
    },
    {
      "y": 27.114873058717677,
      "color": "#908f8faa"
    },
    {
      "y": 21.46953632970407,
      "color": "#908f8faa"
    }
  ],
  "nhnxKyHanDH": [
    30.762207199805637,
    31.180740881611246,
    35.89386953339261,
    36.386084939001115,
    36.624776678873815,
    38.58307821914303,
    39.497862018321264,
    40.50059166145479,
    42.08808231634277,
    42.2836397402261,
    42.30549553777606,
    45.960912539957654,
    47.48969459740461,
    49.0304061089613,
    50.4836509689607,
    51.89517666779868,
    52.62087863986393,
    57.00071536920728,
    58.72733331288582,
    60.20984083714107,
    62.3782728294916,
    63.23603749844764,
    63.442348719548356,
    65.20263687630568,
    71.9829680153052,
    72.88512694128232,
    78.53046367029593
  ],
  "nhnxNKhachS": [
    "SGB",
    "VIB",
    "BAB",
    "ACB",
    "EIB",
    "STB",
    "VBB",
    "TPB",
    "BVB",
    "BID",
    "VCB",
    "LPB",
    "TCB",
    "CTG",
    "VPB",
    "ABB",
    "MBB",
    "PGB",
    "HDB",
    "MSB",
    "OCB",
    "NVB",
    "KLB",
    "SSB",
    "SHB",
    "NAB",
    "VAB"
  ],
  "nhnxNKhachCN": [
    {
      "y": 73.50464179241554,
      "color": "#908f8faa"
    },
    {
      "y": 69.8072080756827,
      "color": "#908f8faa"
    },
    {
      "y": 63.54008993377529,
      "color": "#908f8faa"
    },
    {
      "y": 61.89356692705849,
      "color": "#908f8faa"
    },
    {
      "y": 56.988034738354756,
      "color": "#908f8faa"
    },
    {
      "y": 52.95914093048546,
      "color": "#908f8faa"
    },
    {
      "y": 51.100838404963575,
      "color": "#908f8faa"
    },
    {
      "y": 48.27369838792451,
      "color": "#908f8faa"
    },
    {
      "y": 47.39328501292364,
      "color": "#908f8faa"
    },
    {
      "y": 47.35197030562287,
      "color": "#908f8faa"
    },
    {
      "y": 45.29925123497134,
      "color": "#908f8faa"
    },
    {
      "y": 42.358515982214634,
      "color": "#908f8faa"
    },
    {
      "y": 40.68799251612323,
      "color": "#908f8faa"
    },
    {
      "y": 40.56237932965717,
      "color": "#908f8faa"
    },
    {
      "y": 40.47042486832023,
      "color": "#908f8faa"
    },
    {
      "y": 40.38321673407168,
      "color": "#908f8faa"
    },
    {
      "y": 40.37630803589792,
      "color": "#908f8faa"
    },
    {
      "y": 38.05730615471404,
      "color": "#908f8faa"
    },
    {
      "y": 30.690696948857145,
      "color": "#908f8faa"
    },
    {
      "y": 30.327154286510133,
      "color": "#908f8faa"
    },
    {
      "y": 29.251133673570408,
      "color": "#908f8faa"
    },
    {
      "y": 29.168197974848287,
      "color": "#908f8faa"
    },
    {
      "y": 21.706242225794593,
      "color": "#908f8faa"
    },
    {
      "y": 19.872843835676537,
      "color": "#ED7D31"
    },
    {
      "y": 16.568759057113922,
      "color": "#908f8faa"
    },
    {
      "y": 15.043956332184058,
      "color": "#908f8faa"
    },
    {
      "y": 5.496863509538037,
      "color": "#908f8faa"
    }
  ],
  "nhnxNKhachTC": [
    26.495358207584463,
    30.19279192431731,
    36.45991006622471,
    38.10643307294151,
    43.011965261645244,
    47.04085906951454,
    48.899161595036425,
    51.72630161207549,
    52.606714987076366,
    52.64802969437713,
    54.70074876502866,
    57.64148401778537,
    59.31200748387677,
    59.43762067034283,
    59.52957513167977,
    59.61678326592832,
    59.623691964102086,
    61.94269384528596,
    69.30930305114286,
    69.67284571348986,
    70.74886632642959,
    70.83180202515172,
    78.2937577742054,
    80.12715616432347,
    83.43124094288608,
    84.95604366781593,
    94.50313649046196
  ],
  "nhnxduPhongChung35": [
    37.18,
    41.98,
    44.57,
    44.96,
    43.62,
    46.39,
    45.55,
    46.39,
    46.37,
    42.84,
    39.58,
    38.29,
    37.66,
    38.76,
    39.59,
    39.1,
    40.03,
    37.71,
    37.8,
    35.91,
    32.6
  ],
  "nhnxdpCuThe35": [
    26.02,
    29.87,
    28.69,
    39.69,
    42.45,
    49.33,
    48.1,
    52.51,
    58.72,
    55.83,
    58.68,
    47.21,
    47.39,
    37.9,
    41.23,
    43.77,
    41.76,
    35.88,
    34.08,
    31.11,
    35.4
  ],
  "nhnxduPhongChung25": [
    34.43324437709172,
    38.793145634101315,
    39.21341351982909,
    40.891764998738076,
    38.03259501535156,
    38.69821678589787,
    38.771510320502664,
    37.674339071296394,
    35.46989306639027,
    31.349805350579295,
    24.301197736007406,
    24.236112915573162,
    24.050973569945832,
    24.643831616046285,
    30.05384545353806,
    29.11207182488735,
    27.549226441631504,
    26.310679611650485,
    25.51918273436882,
    26.980800015786212,
    24.127200442323506
  ],
  "nhnxduPhongCthe25": [
    24.09733807478438,
    27.60746530751293,
    25.23518372670542,
    36.10362984500814,
    37.012279063937264,
    41.145627731691455,
    40.9424747484639,
    42.641595511567374,
    44.915359868855184,
    40.85685984065896,
    36.03042776230524,
    29.876894601871264,
    30.267651511379007,
    24.09425917566999,
    31.298622493978378,
    32.589087274278015,
    28.744725738396625,
    25.032362459546924,
    23.011119133317315,
    23.379230520673776,
    26.19574755680437
  ],
  "nhnxCasa": [
    9,
    8,
    11,
    9,
    11,
    9,
    10,
    10,
    9,
    10,
    17,
    11,
    11,
    13,
    13,
    19,
    10,
    11,
    16,
    15,
    11
  ],
  "noXauDates": [
    "Q1.21",
    "Q2.21",
    "Q3.21",
    "Q4.21",
    "Q1.22",
    "Q2.22",
    "Q3.22",
    "Q4.22",
    "Q1.23",
    "Q2.23",
    "Q3.23",
    "Q4.23",
    "Q1.24",
    "Q2.24",
    "Q3.24",
    "Q4.24",
    "Q1.25",
    "Q2.25",
    "Q3.25",
    "Q4.25",
    "Q1.26"
  ],
  "noXauTiLe": [
    1.8,
    1.76,
    1.68,
    1.65,
    1.64,
    1.6,
    1.59,
    1.6,
    1.6,
    1.73,
    1.87,
    1.94,
    1.96,
    1.91,
    1.87,
    1.89,
    1.84,
    1.95,
    1.95,
    2.06,
    2.24
  ],
  "noXauTiLeBaoPhu": [
    63,
    72,
    73,
    85,
    86,
    96,
    94,
    99,
    105,
    99,
    98,
    86,
    85,
    77,
    81,
    83,
    82,
    74,
    72,
    67,
    68
  ],
  "nhTyLeNhomNo2345": [
    1.94,
    1.9,
    1.92,
    1.81,
    1.88,
    1.92,
    1.87,
    1.97,
    2.09,
    2.36,
    3.05,
    3.06,
    3.07,
    3,
    2.47,
    2.54,
    2.67,
    2.8,
    2.89,
    2.74,
    3.02
  ],
  "nhDuPhongRuiRoTinDungNo2345": [
    59,
    66,
    64,
    77,
    75,
    80,
    80,
    80,
    80,
    72,
    60,
    54,
    54,
    49,
    61,
    62,
    56,
    51,
    49,
    50,
    50
  ],
  "nhnxnoNhom3": [
    0.26972708192383343,
    0.20091840758505639,
    0.21422256713271745,
    0.2708049106657303,
    0.3711462933372942,
    0.303188379414984,
    0.3008337856228458,
    0.29459912154637025,
    0.31188737283371826,
    0.33548180822748247,
    0.2361454392284026,
    0.2133257088980977,
    0.1557113487729449,
    0.19024096082391884,
    0.32866346836056004,
    0.09689873465094348,
    0.1440989823889452,
    0.22351079697693713,
    0.14148612191539786,
    0.13730309292963297,
    0.15557490764412818
  ],
  "nhnxnoNhom4": [
    0.34108951327774534,
    0.3408517452376352,
    0.23479538779407205,
    0.2599614279252983,
    0.27733597314198394,
    0.2975406118092437,
    0.23411037248325883,
    0.14261672907151285,
    0.19805599675984395,
    0.2123099522571773,
    0.4462751817295055,
    0.4808355481407921,
    0.4223923875212139,
    0.4059891706931522,
    0.35445352344653913,
    0.33201604227139114,
    0.18071045022717885,
    0.218070371898391,
    0.412200813547984,
    0.24179329761891202,
    0.2568807748352072
  ],
  "nhnxnoNhom5": [
    1.1900294162915472,
    1.2183875210884743,
    1.2357113895029281,
    1.1187668285111003,
    0.9922822446370593,
    1.0000690812587725,
    1.0587611907440482,
    1.1607115623015178,
    1.0890493201659135,
    1.1821995227539965,
    1.1910293575591682,
    1.2435079056441427,
    1.3827118097944413,
    1.3133154621084795,
    1.1889851283189832,
    1.4623048030513468,
    1.5128046261875259,
    1.513344909348917,
    1.3978344862671015,
    1.677064600241893,
    1.823919058320785
  ],
  "choNhanGiaRaPE": 0.9096187466508765,
  "choNhanGiaRaPB": 0.06858434936004534,
  "choNhanGiaRaPS": null,
  "PE": [
    0,
    null,
    null,
    null,
    0,
    0,
    0,
    0,
    0,
    0,
    0,
    0,
    0,
    0,
    0,
    0,
    0,
    0,
    0,
    0,
    21.2,
    23.9,
    19.3,
    25.9,
    20.4,
    17.3,
    15.9,
    16.6,
    16.6,
    16.2,
    18.3,
    16.2,
    13.7,
    11.2,
    10.2,
    9.9,
    7.8,
    7.5,
    8.3,
    null,
    null
  ],
  "PETb": [
    7.5,
    7.5,
    7.5,
    7.5,
    7.5,
    7.5,
    7.5,
    7.5,
    7.5,
    7.5,
    7.5,
    7.5,
    7.5,
    7.5,
    7.5,
    7.5,
    7.5,
    7.5,
    7.5,
    7.5,
    7.5,
    7.5,
    7.5,
    7.5,
    7.5,
    7.5,
    7.5,
    7.5,
    7.5,
    7.5,
    7.5,
    7.5,
    7.5,
    7.5,
    7.5,
    7.5,
    7.5,
    7.5,
    7.5,
    7.5,
    7.5
  ],
  "PB": [
    null,
    0,
    0,
    0,
    0,
    0,
    0,
    0,
    0,
    0,
    0,
    0,
    0,
    0,
    0,
    0,
    0,
    0,
    0,
    0,
    2.4,
    3.3,
    3,
    3.6,
    2.8,
    2.7,
    2.5,
    2.6,
    2.4,
    2,
    2.1,
    2,
    1.7,
    1.6,
    1.4,
    1.4,
    1.4,
    1.3,
    1.4,
    null,
    null
  ],
  "PBTb": [
    1.3,
    1.3,
    1.3,
    1.3,
    1.3,
    1.3,
    1.3,
    1.3,
    1.3,
    1.3,
    1.3,
    1.3,
    1.3,
    1.3,
    1.3,
    1.3,
    1.3,
    1.3,
    1.3,
    1.3,
    1.3,
    1.3,
    1.3,
    1.3,
    1.3,
    1.3,
    1.3,
    1.3,
    1.3,
    1.3,
    1.3,
    1.3,
    1.3,
    1.3,
    1.3,
    1.3,
    1.3,
    1.3,
    1.3,
    1.3,
    1.3
  ],
  "PS": [
    null,
    null,
    null,
    null,
    null,
    null,
    null,
    null,
    null,
    null,
    null,
    null,
    null,
    null,
    null,
    null,
    null,
    null,
    null,
    null,
    null,
    null,
    null,
    null,
    null,
    null,
    null,
    null,
    null,
    null,
    null,
    null,
    null,
    null,
    null,
    null,
    null,
    null,
    null,
    null,
    null
  ],
  "PSTb": [
    null,
    null,
    null,
    null,
    null,
    null,
    null,
    null,
    null,
    null,
    null,
    null,
    null,
    null,
    null,
    null,
    null,
    null,
    null,
    null,
    null,
    null,
    null,
    null,
    null,
    null,
    null,
    null,
    null,
    null,
    null,
    null,
    null,
    null,
    null,
    null,
    null,
    null,
    null,
    null,
    null
  ],
  "soCoPhieuLuuHanh": 2845000000,
  "isNganHang": true,
  "isChungKhoan": false,
  "vec11400Year": {},
  "tangTruongHangTonKhoKep": null,
  "lctThuanHDSXKD": [
    4270,
    -227,
    -69,
    33966,
    -35291,
    9608,
    2997,
    -2389,
    -2027,
    5533,
    -1154,
    7778,
    120,
    8570,
    7865,
    -3082,
    32950,
    30423
  ],
  "lctThuanHDDauTu": [
    -171,
    -176,
    -33,
    -351,
    -1462,
    -209,
    997,
    -104,
    -20,
    -49,
    -700,
    96,
    -156,
    105,
    -257,
    -290,
    -227,
    4074
  ],
  "lctThuanHDTC": [
    -500,
    0,
    -355,
    -168,
    0,
    0,
    0,
    -125,
    0,
    0,
    1643,
    1681,
    1407,
    2406,
    3611,
    504,
    0,
    100
  ],
  "lctThuanTrongKy": [
    3599,
    -403,
    -456,
    33447,
    -36754,
    9399,
    3994,
    -2618,
    -2047,
    5484,
    -211,
    9555,
    1371,
    11081,
    11218,
    -2868,
    32724,
    34597
  ],
  "hangTonKho": [
    0,
    0,
    0,
    0,
    0,
    0,
    0,
    0,
    0,
    0,
    0,
    0,
    0,
    0,
    0,
    0,
    0,
    0
  ],
  "hangTonKhoVongQuay": [
    null,
    null,
    null,
    null,
    null,
    null,
    null,
    null,
    null,
    null,
    null,
    null,
    null,
    null,
    null,
    null,
    null,
    null
  ],
  "coTucLNST": [
    173,
    460,
    629,
    126,
    53,
    152,
    87,
    92,
    117,
    305,
    493,
    1098,
    1360,
    2607,
    4053,
    3677,
    4816,
    5510
  ],
  "coTucDaTra": [
    500,
    0,
    355,
    168,
    0,
    0,
    0,
    125,
    0,
    0,
    0,
    0,
    0,
    0,
    0,
    0,
    0,
    0
  ],
  "coTucTiLeDaTra": [
    289,
    0,
    56,
    134,
    0,
    0,
    0,
    136,
    0,
    0,
    0,
    0,
    0,
    0,
    0,
    0,
    0,
    0
  ],
  "newFiscalDateYear": [
    "2008-12-31",
    "2009-12-31",
    "2010-12-31",
    "2011-12-31",
    "2012-12-31",
    "2013-12-31",
    "2014-12-31",
    "2015-12-31",
    "2016-12-31",
    "2017-12-31",
    "2018-12-31",
    "2019-12-31",
    "2020-12-31",
    "2021-12-31",
    "2022-12-31",
    "2023-12-31",
    "2024-12-31",
    "2025-12-31"
  ]
}