{"data":[{"code":"L61","shareholderType":"COMPANY","shareholderName":"LILAMA","roleType":"Cổ đông lớn","enRoleType":"Major Shareholder","numberOfShares":3113862,"ownershipPct":41.10057812623743,"effectiveDate":"2019-05-23"},{"code":"L61","shareholderType":"PERSON","shareholderName":"Cao Đài","roleType":"Cổ đông lớn","enRoleType":"Major Shareholder","numberOfShares":1168566,"ownershipPct":15.42417042844698,"effectiveDate":"2022-09-16"},{"code":"L61","shareholderType":"PERSON","shareholderName":"Lê Đức Lộc","roleType":"Cổ đông lớn","enRoleType":"Major Shareholder","numberOfShares":461148,"ownershipPct":6.08679813098915,"effectiveDate":"2019-09-24"}],"currentPage":1,"size":15,"totalElements":3,"totalPages":1}