{
  "data": [
    {
      "code": "SDY",
      "shareholderType": "PERSON",
      "shareholderName": "Trần Quang Ninh",
      "roleType": "Cổ đông lớn",
      "enRoleType": "Major Shareholder",
      "numberOfShares": 1000000,
      "ownershipPct": 22.22222222222222,
      "effectiveDate": "2024-06-28"
    },
    {
      "code": "SDY",
      "shareholderType": "PERSON",
      "shareholderName": "Trần Anh Minh",
      "roleType": "Cổ đông lớn",
      "enRoleType": "Major Shareholder",
      "numberOfShares": 1000000,
      "ownershipPct": 22.22222222222222,
      "effectiveDate": "2017-12-28"
    },
    {
      "code": "SDY",
      "shareholderType": "PERSON",
      "shareholderName": "Trần Hạnh Nguyên",
      "roleType": "Cổ đông lớn",
      "enRoleType": "Major Shareholder",
      "numberOfShares": 805500,
      "ownershipPct": 17.9,
      "effectiveDate": "2017-12-28"
    },
    {
      "code": "SDY",
      "shareholderType": "PERSON",
      "shareholderName": "Trần Đức Minh",
      "roleType": "Cổ đông lớn",
      "enRoleType": "Major Shareholder",
      "numberOfShares": 600000,
      "ownershipPct": 13.333333333333334,
      "effectiveDate": "2015-02-13"
    },
    {
      "code": "SDY",
      "shareholderType": "PERSON",
      "shareholderName": "Trần Quang Huy",
      "roleType": "Cổ đông lớn",
      "enRoleType": "Major Shareholder",
      "numberOfShares": 407100,
      "ownershipPct": 9.046666666666667,
      "effectiveDate": "2020-06-30"
    },
    {
      "code": "SDY",
      "shareholderType": "PERSON",
      "shareholderName": "Trần Thị Kim Thoa",
      "roleType": "Cổ đông lớn",
      "enRoleType": "Major Shareholder",
      "numberOfShares": 305000,
      "ownershipPct": 6.777777777777778,
      "effectiveDate": "2017-12-26"
    },
    {
      "code": "SDY",
      "shareholderType": "PERSON",
      "shareholderName": "Đặng Đôn Triển",
      "roleType": "Cổ đông lớn",
      "enRoleType": "Major Shareholder",
      "numberOfShares": 199000,
      "ownershipPct": 4.4222222222222225,
      "effectiveDate": "2015-04-16"
    },
    {
      "code": "SDY",
      "shareholderType": "COMPANY",
      "shareholderName": "CTCP Sông Đà 4",
      "roleType": "Cổ đông lớn",
      "enRoleType": "Major Shareholder",
      "numberOfShares": 58200,
      "ownershipPct": 1.2933333333333332,
      "effectiveDate": "2008-09-09"
    }
  ],
  "currentPage": 1,
  "size": 10,
  "totalElements": 8,
  "totalPages": 1
}