{"data":[{"code":"SKH","shareholderType":"COMPANY","shareholderName":"Công ty TNHH Nhà nước MTV Yến sào Khánh Hòa","roleType":"Cổ đông lớn","enRoleType":"Major Shareholder","numberOfShares":16850000,"ownershipPct":51.06060606060606,"effectiveDate":"2020-06-30"},{"code":"SKH","shareholderType":"PERSON","shareholderName":"Lê Huỳnh Phụng","roleType":"Thành viên HĐQT","enRoleType":"Board member","numberOfShares":3984900,"ownershipPct":12.075454545454546,"effectiveDate":"2022-12-31"},{"code":"SKH","shareholderType":"PERSON","shareholderName":"Nguyễn Xuân Anh","roleType":"Thành viên HĐQT","enRoleType":"Board member","numberOfShares":3960000,"ownershipPct":12,"effectiveDate":"2022-12-31"},{"code":"SKH","shareholderType":"COMPANY","shareholderName":"Công ty TNHH Bao bì NGK Crown Đồng Nai","roleType":"Cổ đông lớn","enRoleType":"Major Shareholder","numberOfShares":3300000,"ownershipPct":10,"effectiveDate":"2020-06-30"},{"code":"SKH","shareholderType":"COMPANY","shareholderName":"Công ty TNHH NHT","roleType":"Cổ đông lớn","enRoleType":"Major Shareholder","numberOfShares":1557400,"ownershipPct":4.71939393939394,"effectiveDate":"2022-11-29"}],"currentPage":1,"size":10,"totalElements":5,"totalPages":1}