{
  "data": [
    {
      "code": "TIS",
      "shareholderType": "COMPANY",
      "shareholderName": "TCT Thép Việt Nam",
      "roleType": "Cổ đông lớn",
      "enRoleType": "Major Shareholder",
      "numberOfShares": 119600000,
      "ownershipPct": 65.00392143221683,
      "effectiveDate": "2020-06-30"
    },
    {
      "code": "TIS",
      "shareholderType": "COMPANY",
      "shareholderName": "Công ty cổ phần thương mại Thái Hưng",
      "roleType": "Cổ đông lớn",
      "enRoleType": "Major Shareholder",
      "numberOfShares": 36800000,
      "ownershipPct": 20.001206594528256,
      "effectiveDate": "2019-02-14"
    }
  ],
  "currentPage": 1,
  "size": 10,
  "totalElements": 2,
  "totalPages": 1
}