{"11000":{"numericValue":61819637158,"fiscalDate":"2015-12-31"},"11100":{"numericValue":8754890028,"fiscalDate":"2015-12-31"},"11110":{"numericValue":1226514364,"fiscalDate":"2015-12-31"},"11120":{"numericValue":7528375664,"fiscalDate":"2015-12-31"},"11200":{"numericValue":0,"fiscalDate":"2015-12-31"},"11210":{"numericValue":0,"fiscalDate":"2015-12-31"},"11290":{"numericValue":0,"fiscalDate":"2015-12-31"},"11300":{"numericValue":33067546056,"fiscalDate":"2015-12-31"},"11310":{"numericValue":29944062635,"fiscalDate":"2015-12-31"},"11320":{"numericValue":576978000,"fiscalDate":"2015-12-31"},"11330":{"numericValue":0,"fiscalDate":"2015-12-31"},"11340":{"numericValue":0,"fiscalDate":"2015-12-31"},"11345":{"numericValue":0,"fiscalDate":"2015-12-31"},"11350":{"numericValue":2658220768,"fiscalDate":"2015-12-31"},"11390":{"numericValue":-111715347,"fiscalDate":"2015-12-31"},"11400":{"numericValue":19923710826,"fiscalDate":"2015-12-31"},"11410":{"numericValue":19923710826,"fiscalDate":"2015-12-31"},"11490":{"numericValue":0,"fiscalDate":"2015-12-31"},"11500":{"numericValue":73490248,"fiscalDate":"2015-12-31"},"11510":{"numericValue":73490248,"fiscalDate":"2015-12-31"},"11520":{"numericValue":0,"fiscalDate":"2015-12-31"},"11540":{"numericValue":0,"fiscalDate":"2015-12-31"},"11570":{"numericValue":0,"fiscalDate":"2015-12-31"},"11580":{"numericValue":0,"fiscalDate":"2015-12-31"},"12000":{"numericValue":348328588330,"fiscalDate":"2015-12-31"},"12100":{"numericValue":168017511,"fiscalDate":"2015-12-31"},"12110":{"numericValue":0,"fiscalDate":"2015-12-31"},"12111":{"numericValue":0,"fiscalDate":"2015-12-31"},"12120":{"numericValue":0,"fiscalDate":"2015-12-31"},"12130":{"numericValue":0,"fiscalDate":"2015-12-31"},"12140":{"numericValue":0,"fiscalDate":"2015-12-31"},"12180":{"numericValue":168017511,"fiscalDate":"2015-12-31"},"12190":{"numericValue":0,"fiscalDate":"2015-12-31"},"12200":{"numericValue":330264571478,"fiscalDate":"2015-12-31"},"12210":{"numericValue":330086023091,"fiscalDate":"2015-12-31"},"12220":{"numericValue":568173305208,"fiscalDate":"2015-12-31"},"12230":{"numericValue":-238087282117,"fiscalDate":"2015-12-31"},"12240":{"numericValue":0,"fiscalDate":"2015-12-31"},"12250":{"numericValue":0,"fiscalDate":"2015-12-31"},"12260":{"numericValue":0,"fiscalDate":"2015-12-31"},"12270":{"numericValue":178548387,"fiscalDate":"2015-12-31"},"12280":{"numericValue":180000000,"fiscalDate":"2015-12-31"},"12290":{"numericValue":-1451613,"fiscalDate":"2015-12-31"},"12300":{"numericValue":0,"fiscalDate":"2015-12-31"},"12400":{"numericValue":0,"fiscalDate":"2015-12-31"},"12410":{"numericValue":0,"fiscalDate":"2015-12-31"},"12420":{"numericValue":0,"fiscalDate":"2015-12-31"},"12440":{"numericValue":568183821,"fiscalDate":"2015-12-31"},"12450":{"numericValue":0,"fiscalDate":"2015-12-31"},"12460":{"numericValue":568183821,"fiscalDate":"2015-12-31"},"12500":{"numericValue":0,"fiscalDate":"2015-12-31"},"12510":{"numericValue":0,"fiscalDate":"2015-12-31"},"12520":{"numericValue":0,"fiscalDate":"2015-12-31"},"12580":{"numericValue":0,"fiscalDate":"2015-12-31"},"12590":{"numericValue":0,"fiscalDate":"2015-12-31"},"12595":{"numericValue":0,"fiscalDate":"2015-12-31"},"12600":{"numericValue":17327815520,"fiscalDate":"2015-12-31"},"12610":{"numericValue":17327815520,"fiscalDate":"2015-12-31"},"12620":{"numericValue":0,"fiscalDate":"2015-12-31"},"12630":{"numericValue":0,"fiscalDate":"2015-12-31"},"12680":{"numericValue":0,"fiscalDate":"2015-12-31"},"12690":{"numericValue":0,"fiscalDate":"2015-12-31"},"12700":{"numericValue":410148225488,"fiscalDate":"2015-12-31"},"13000":{"numericValue":266227520453,"fiscalDate":"2015-12-31"},"13100":{"numericValue":33757492815,"fiscalDate":"2015-12-31"},"13110":{"numericValue":18151632000,"fiscalDate":"2015-12-31"},"13120":{"numericValue":2322187525,"fiscalDate":"2015-12-31"},"13130":{"numericValue":170362052,"fiscalDate":"2015-12-31"},"13140":{"numericValue":1177512620,"fiscalDate":"2015-12-31"},"13150":{"numericValue":5020645321,"fiscalDate":"2015-12-31"},"13160":{"numericValue":0,"fiscalDate":"2015-12-31"},"13170":{"numericValue":0,"fiscalDate":"2015-12-31"},"13180":{"numericValue":0,"fiscalDate":"2015-12-31"},"13190":{"numericValue":4301912389,"fiscalDate":"2015-12-31"},"13197":{"numericValue":0,"fiscalDate":"2015-12-31"},"13199":{"numericValue":0,"fiscalDate":"2015-12-31"},"13200":{"numericValue":0,"fiscalDate":"2015-12-31"},"13210":{"numericValue":0,"fiscalDate":"2015-12-31"},"13220":{"numericValue":0,"fiscalDate":"2015-12-31"},"13300":{"numericValue":232470027638,"fiscalDate":"2015-12-31"},"13310":{"numericValue":0,"fiscalDate":"2015-12-31"},"13311":{"numericValue":0,"fiscalDate":"2015-12-31"},"13312":{"numericValue":11205608422,"fiscalDate":"2015-12-31"},"13313":{"numericValue":0,"fiscalDate":"2015-12-31"},"13320":{"numericValue":0,"fiscalDate":"2015-12-31"},"13330":{"numericValue":67539791095,"fiscalDate":"2015-12-31"},"13340":{"numericValue":153724628121,"fiscalDate":"2015-12-31"},"13343":{"numericValue":0,"fiscalDate":"2015-12-31"},"13346":{"numericValue":0,"fiscalDate":"2015-12-31"},"13350":{"numericValue":0,"fiscalDate":"2015-12-31"},"13360":{"numericValue":0,"fiscalDate":"2015-12-31"},"13370":{"numericValue":0,"fiscalDate":"2015-12-31"},"14000":{"numericValue":143920705035,"fiscalDate":"2015-12-31"},"14100":{"numericValue":125347599035,"fiscalDate":"2015-12-31"},"14110":{"numericValue":124108000000,"fiscalDate":"2015-12-31"},"14120":{"numericValue":0,"fiscalDate":"2015-12-31"},"14130":{"numericValue":0,"fiscalDate":"2015-12-31"},"14140":{"numericValue":0,"fiscalDate":"2015-12-31"},"14145":{"numericValue":0,"fiscalDate":"2015-12-31"},"14148":{"numericValue":124108000000,"fiscalDate":"2015-12-31"},"14149":{"numericValue":0,"fiscalDate":"2015-12-31"},"14150":{"numericValue":0,"fiscalDate":"2015-12-31"},"14160":{"numericValue":0,"fiscalDate":"2015-12-31"},"14170":{"numericValue":516869839,"fiscalDate":"2015-12-31"},"14180":{"numericValue":0,"fiscalDate":"2015-12-31"},"14190":{"numericValue":0,"fiscalDate":"2015-12-31"},"14191":{"numericValue":516869839,"fiscalDate":"2015-12-31"},"14193":{"numericValue":0,"fiscalDate":"2015-12-31"},"14200":{"numericValue":722729196,"fiscalDate":"2015-12-31"},"14201":{"numericValue":0,"fiscalDate":"2015-12-31"},"14220":{"numericValue":0,"fiscalDate":"2015-12-31"},"14230":{"numericValue":722729196,"fiscalDate":"2015-12-31"},"14240":{"numericValue":0,"fiscalDate":"2015-12-31"},"14300":{"numericValue":18573106000,"fiscalDate":"2015-12-31"},"14310":{"numericValue":2613240908,"fiscalDate":"2015-12-31"},"14320":{"numericValue":0,"fiscalDate":"2015-12-31"},"14330":{"numericValue":18573106000,"fiscalDate":"2015-12-31"},"14400":{"numericValue":410148225488,"fiscalDate":"2015-12-31"},"15000":{"numericValue":0,"fiscalDate":"2015-12-31"},"21000":{"numericValue":99655050564,"fiscalDate":"2015-12-31"},"21001":{"numericValue":99610790068,"fiscalDate":"2015-12-31"},"21090":{"numericValue":44260496,"fiscalDate":"2015-12-31"},"21500":{"numericValue":234975877,"fiscalDate":"2015-12-31"},"21900":{"numericValue":43142657,"fiscalDate":"2015-12-31"},"22051":{"numericValue":1483222623,"fiscalDate":"2015-12-31"},"22052":{"numericValue":0,"fiscalDate":"2015-12-31"},"22070":{"numericValue":1483222623,"fiscalDate":"2015-12-31"},"22100":{"numericValue":73557334776,"fiscalDate":"2015-12-31"},"22110":{"numericValue":6030679751,"fiscalDate":"2015-12-31"},"22200":{"numericValue":9320138880,"fiscalDate":"2015-12-31"},"22230":{"numericValue":0,"fiscalDate":"2015-12-31"},"22500":{"numericValue":4238834181,"fiscalDate":"2015-12-31"},"22509":{"numericValue":0,"fiscalDate":"2015-12-31"},"22510":{"numericValue":4238834181,"fiscalDate":"2015-12-31"},"22515":{"numericValue":0,"fiscalDate":"2015-12-31"},"22900":{"numericValue":0,"fiscalDate":"2015-12-31"},"23000":{"numericValue":5258698391,"fiscalDate":"2015-12-31"},"23001":{"numericValue":250,"fiscalDate":"2015-12-31"},"23003":{"numericValue":5258698391,"fiscalDate":"2015-12-31"},"23100":{"numericValue":26053455292,"fiscalDate":"2015-12-31"},"23110":{"numericValue":6698778357,"fiscalDate":"2015-12-31"},"23200":{"numericValue":0,"fiscalDate":"2015-12-31"},"23300":{"numericValue":0,"fiscalDate":"2015-12-31"},"23500":{"numericValue":0,"fiscalDate":"2015-12-31"},"23800":{"numericValue":6741921014,"fiscalDate":"2015-12-31"},"23810":{"numericValue":0,"fiscalDate":"2015-12-31"},"23900":{"numericValue":43142657,"fiscalDate":"2015-12-31"},"30100":{"numericValue":126743020341,"fiscalDate":"2015-12-31"},"30200":{"numericValue":-29337514603,"fiscalDate":"2015-12-31"},"30300":{"numericValue":-20856921963,"fiscalDate":"2015-12-31"},"30400":{"numericValue":-4275228427,"fiscalDate":"2015-12-31"},"30500":{"numericValue":-2036233858,"fiscalDate":"2015-12-31"},"30600":{"numericValue":1052053748,"fiscalDate":"2015-12-31"},"30700":{"numericValue":-49509389744,"fiscalDate":"2015-12-31"},"31100":{"numericValue":0,"fiscalDate":"2015-12-31"},"31101":{"numericValue":0,"fiscalDate":"2015-12-31"},"31102":{"numericValue":0,"fiscalDate":"2015-12-31"},"31110":{"numericValue":0,"fiscalDate":"2015-12-31"},"31111":{"numericValue":0,"fiscalDate":"2015-12-31"},"31120":{"numericValue":0,"fiscalDate":"2015-12-31"},"31130":{"numericValue":0,"fiscalDate":"2015-12-31"},"31140":{"numericValue":0,"fiscalDate":"2015-12-31"},"31150":{"numericValue":0,"fiscalDate":"2015-12-31"},"31160":{"numericValue":0,"fiscalDate":"2015-12-31"},"31170":{"numericValue":0,"fiscalDate":"2015-12-31"},"31180":{"numericValue":0,"fiscalDate":"2015-12-31"},"31190":{"numericValue":0,"fiscalDate":"2015-12-31"},"31200":{"numericValue":0,"fiscalDate":"2015-12-31"},"32000":{"numericValue":21779785494,"fiscalDate":"2015-12-31"},"32100":{"numericValue":-1454907272,"fiscalDate":"2015-12-31"},"32200":{"numericValue":0,"fiscalDate":"2015-12-31"},"32300":{"numericValue":0,"fiscalDate":"2015-12-31"},"32400":{"numericValue":0,"fiscalDate":"2015-12-31"},"32500":{"numericValue":0,"fiscalDate":"2015-12-31"},"32600":{"numericValue":0,"fiscalDate":"2015-12-31"},"32700":{"numericValue":224670811,"fiscalDate":"2015-12-31"},"33000":{"numericValue":-1230236461,"fiscalDate":"2015-12-31"},"33100":{"numericValue":0,"fiscalDate":"2015-12-31"},"33200":{"numericValue":0,"fiscalDate":"2015-12-31"},"33300":{"numericValue":0,"fiscalDate":"2015-12-31"},"33400":{"numericValue":-12338890000,"fiscalDate":"2015-12-31"},"33500":{"numericValue":0,"fiscalDate":"2015-12-31"},"33600":{"numericValue":0,"fiscalDate":"2015-12-31"},"33710":{"numericValue":0,"fiscalDate":"2015-12-31"},"34000":{"numericValue":-12338890000,"fiscalDate":"2015-12-31"},"35000":{"numericValue":8210659033,"fiscalDate":"2015-12-31"},"36000":{"numericValue":544230995,"fiscalDate":"2015-12-31"},"36100":{"numericValue":0,"fiscalDate":"2015-12-31"},"37000":{"numericValue":8754890028,"fiscalDate":"2015-12-31"},"412320":{"numericValue":0,"fiscalDate":"2015-12-31"},"412541":{"numericValue":0,"fiscalDate":"2015-12-31"},"431100":{"numericValue":0,"fiscalDate":"2015-12-31"},"431400":{"numericValue":0,"fiscalDate":"2015-12-31"},"611530":{"numericValue":0,"fiscalDate":"2015-12-31"}}