{"code":"CQN","floor":"UPCOM","vnName":"Cảng Quảng Ninh","enName":"Quang Ninh Port Joint Stock Company","foundDate":"2014-08-22","taxCode":"5700100231","registrationCode":"5700100231","vnAddress":"đường cái lân, Bãi Cháy, Hạ Long, Quảng Ninh, VIỆT NAM","enAddress":"Quang Ninh, VIETNAM","phone":"+84 (203) 36283288","fax":"+84 (203) ","website":"www.quangninhport.com. vn","email":"qnp@quangninhport.com. vn","employees":668,"vnSummary":"Ngày 29/08/1977, Bộ giao thông vận tải quyết định thành lập Công ty Cảng Quảng Ninh và chuyển Ty cảng Vụ, Hoa tiêu Hồng Gai- Cẩm Phả về Cảng Quảng Ninh quản lý. Ngày 22/08/2014, công ty nhận giấy chứng nhận đăng ký doanh nghiệp chuyển đổi từ Công ty TNHH 1 thành viên sang công ty cổ phần. Ngày 17/7/2020,sở giao dịch chứng khoán Hà Nội chấp thuận đăng ký giao dịch cổ phiếu của Cảng Quảng Ninh trên sàn Upcom. Ngành Nghề kinh doanh chính bao gồm: dịch vụ xếp dỡ hàng hóa, dịch vụ kho bãi, dịch vụ đại lý vận tải và giao nhận hàng hóa, dịch vụ xuất nhập khẩu, vận tải hàng hóa đa phương thức, dịch vụ hàng hải, kinh doanh nông sản. Thành tích nổi bật: Trong nhiều năm liền, cảng Quảng Ninh luôn là một trong những cảng dẫn đầu cả nước về hàng hóa thông qua.","enSummary":"","companyId":"5240","industry_classification":[{"vietnameseName":"Dịch vụ giao nhận"},{"vietnameseName":"Giao thông công nghiệp"},{"vietnameseName":"Công nghiệp"},{"vietnameseName":"Hàng hóa và dịch vụ công nghiệp"}]}