{
  "code": "VNF",
  "floor": "HNX",
  "logo": "https://azfincdn.truyenhayaz.com/logo/vnf.png",
  "vnName": "VINAFREIGHT",
  "enName": "Vinafreight",
  "foundDate": "2002-01-14",
  "taxCode": "0302511219",
  "registrationCode": "0302511219",
  "vnAddress": "tầng 8 tòa nhà Phú Nhuận Plaza, số 82 Trần Huy Liệu, P. 15, Phú Nhuận, TP Hồ Chí Minh, VIỆT NAM",
  "enAddress": "Ho Chi Minh City, VIETNAM",
  "phone": "+84 (28) 38446409",
  "fax": "+84 (28) 38488359",
  "website": "www.vinafreight.com",
  "email": "mngt@vinafreight.com.vn",
  "employees": 229,
  "branches": 2,
  "vnSummary": "\nCông ty Cổ phần Vận tải Ngoại thương (Vinafreight) được thành lập vào năm 2001. Công ty tập trung chủ yếu vào lĩnh vực kinh doanh các dịch vụ vận tải hàng không và hàng hải, trong đó doanh thu từ lĩnh vực kinh doanh dịch vụ hàng không chiếm 70% tổng doanh thu hàng năm của Công ty với thị trường hoạt động chủ yếu tại thành phố Hồ Chí Minh. Công ty Cổ phần Vận tải Ngoại thương (Vinafreight) là một trong những công ty vận tải hàng không lớn nhất khu vực thành phố Hồ Chí Minh, đứng thứ hai trong xếp hạng của Singapore Airline và thứ ba theo xếp hạng của Malaysia Airline và China International. Công ty đang là đối tác của các nhà cung cấp dịch vụ vận tải hàng không, đường biển lớn trên thế giới như: Singapore Airlines, Vietnam Airlines, Eva Airways, Cathay Pacific Airways, AirFrance, Bristish Airways, Philippines Airways, Lufthansa German Airlines, China Airlines...NYK Line, CMA, Maersk…với các đối thủ cạnh tranh chính như Gemadept, Vitranschart, Samtra, Saigonship.",
  "enSummary": "",
  "companyId": "2517",
  "industry_classification": [
    {
      "vietnameseName": "Giao thông công nghiệp"
    },
    {
      "vietnameseName": "Công nghiệp"
    },
    {
      "vietnameseName": "Hàng hóa và dịch vụ công nghiệp"
    },
    {
      "vietnameseName": "Dịch vụ vận tải"
    }
  ]
}